b_stage_deployment/__init__.py
b_stage_deployment/function.py
b_stage_deployment/resource.py
b_stage_deployment/source/__init__.py
b_stage_deployment/source/action.py
b_stage_deployment/source/cfnresponse.py
b_stage_deployment/source/index.py
b_stage_deployment_test/tests/__init__.py
b_stage_deployment_test/tests/test_deployed.py
b_stage_deployment-1.0.1.dist-info/LICENSE
b_stage_deployment-1.0.1.dist-info/METADATA
b_stage_deployment-1.0.1.dist-info/WHEEL
b_stage_deployment-1.0.1.dist-info/top_level.txt
b_stage_deployment-1.0.1.dist-info/RECORD
