Metadata-Version: 2.1
Name: b-stage-deployment
Version: 1.0.1
Summary: AWS CDK resource that creates a stage deployment. Original one has too many bugs.
Home-page: https://github.com/biomapas/B.StageDeployment.git
Author: Laimonas Sutkus
Author-email: laimonas.sutkus@biomapas.com
License: Apache License 2.0
Keywords: AWS API Gateway Stage Deployment
Classifier: Programming Language :: Python :: 3
Classifier: Operating System :: OS Independent
License-File: LICENSE
Requires-Dist: boto3 <2.0.0,>=1.16.0
Requires-Dist: aws-cdk-lib <3.0.0,>=2.0.0
Requires-Dist: aws-cdk-constructs <3.0.0,>=2.0.0
